[
  {
    "id": 1,
    "title": "Remera Spiderman",
    "category": "remeras",
    "description": "Remera De Spiderman Ultra Algodon",
    "size": "M",
    "price": 29300,
    "thumbnail": "/img/remera1.webp",
    "code": 20231,
    "stock": 15
  },
  {
    "id": 4,
    "title": "Remera Spiderman Modelo Alterno",
    "category": "remeras",
    "description": "Remera De Spiderman con detalles en 3D",
    "size": "XL",
    "price": 29500,
    "thumbnail": "/img/remera2.webp",
    "code": 20234,
    "stock": 15
  },
  {
    "id": 5,
    "title": "Remera Spiderman Modelo Cool",
    "category": "remeras",
    "description": "Remera De Spiderman Color",
    "size": "L",
    "price": 27600,
    "thumbnail": "/img/remera5.webp",
    "code": 20235,
    "stock": 30
  },
  {
    "id": 87,
    "title": "Buzo Spiderman Modelo Spacial",
    "category": "Buzo",
    "description": "Buzo De Spiderman Color Spacial",
    "size": "L",
    "price": 27600,
    "thumbnail": "/img/buzo1.webp",
    "code": 20235,
    "stock": 30
  },
  {
    "id": 31,
    "title": "Mascara Spider-man",
    "category": "Mascaras",
    "size": "M 3/4",
    "code": "52336",
    "description": "Mascara Spiderman Ultra realista",
    "price": 102555,
    "stock": "50",
    "thumbnail": "/img/macara2.webp"
  },
  {
    "id": 32,
    "title": "Mascara Spider-man tipo color alternativo",
    "category": "Mascaras",
    "size": "M 3/8",
    "code": "533653",
    "description": "Mascara de Spiderman color alternativo",
    "price": 150000,
    "stock": "10",
    "thumbnail": "/img/mascara1.webp"
  },
  {
    "id": 33,
    "title": "Gorro Spiderman",
    "category": "Gorros",
    "size": "Unico",
    "status": true,
    "code": "3333666",
    "description": "Gorro Spiderman ",
    "price": 1230,
    "stock": "12",
    "thumbnail": "/img/gorro1.webp"
  },
  {
    "id": 39,
    "title": "Zapatilla de Spiderman",
    "category": "Zapatilla",
    "size": "39",
    "status": true,
    "code": "5566",
    "description": "Zapatilla de Spiderman Cuero",
    "price": 1230,
    "stock": "12",
    "thumbnail": "/img/zapatilla4.webp"
  },
  {
    "id": 3553,
    "title": "Zapatilla de Spiderman Luminosa",
    "category": "Zapatilla",
    "size": "43",
    "status": true,
    "code": "4223",
    "description": "Zapatilla de Spiderman Luminosa",
    "price": 1230,
    "stock": "12",
    "thumbnail": "/img/zapatilla5.webp"
  },
  {
    "id": 313,
    "title": "Zapatilla de Spiderman Moderna",
    "category": "Zapatilla",
    "size": "40",
    "status": true,
    "code": "6933",
    "description": "Zapatilla de Spiderman Moderna",
    "price": 1230,
    "stock": "12",
    "thumbnail": "/img/zapatilla6.webp"
  },
  {
    "id": 314,
    "title": "sabanas caballeros del zodiaco",
    "category": "sabanas",
    "size": "king",
    "status": true,
    "code": "1665",
    "description": "sabanas",
    "price": 1235,
    "stock": "111152",
    "thumbnail": "/img/618dba436733673b0f2d46072db3dce7"
  }
]